README.txt
setup.py
collective/__init__.py
collective.js.galleryview.egg-info/PKG-INFO
collective.js.galleryview.egg-info/SOURCES.txt
collective.js.galleryview.egg-info/dependency_links.txt
collective.js.galleryview.egg-info/entry_points.txt
collective.js.galleryview.egg-info/namespace_packages.txt
collective.js.galleryview.egg-info/not-zip-safe
collective.js.galleryview.egg-info/requires.txt
collective.js.galleryview.egg-info/top_level.txt
collective/js/__init__.py
collective/js/galleryview/__init__.py
collective/js/galleryview/configure.zcml
collective/js/galleryview/resources/CHANGELOG.txt
collective/js/galleryview/resources/LICENSE.txt
collective/js/galleryview/resources/galleryview.css
collective/js/galleryview/resources/jquery.galleryview-2.0-pack.js
collective/js/galleryview/resources/jquery.galleryview-2.0.js
collective/js/galleryview/resources/jquery.timers-1.1.2.js
collective/js/galleryview/resources/loader.gif
collective/js/galleryview/resources/themes/dark/next.gif
collective/js/galleryview/resources/themes/dark/panel-nav-next.gif
collective/js/galleryview/resources/themes/dark/panel-nav-prev.gif
collective/js/galleryview/resources/themes/dark/prev.gif
collective/js/galleryview/resources/themes/light/next.gif
collective/js/galleryview/resources/themes/light/panel-nav-next.gif
collective/js/galleryview/resources/themes/light/panel-nav-prev.gif
collective/js/galleryview/resources/themes/light/prev.gif
docs/HISTORY.txt