Metadata-Version: 1.0
Name: collective.js.galleryview
Version: 0.5.1
Summary: GalleryView aims to provide jQuery users with a flexible, attractive content gallery that is both easy to implement and a snap to customize.
Home-page: https://svn.plone.org/svn/collective/collective.js.galleryview
Author: JeanMichel FRANCOIS
Author-email: jeanmichel.francois@makina-corpus.com
License: MIT
Platform: UNKNOWN
Classifier: Programming Language :: Python
